branch_storm/__init__.py
branch_storm/__init__.pyi
branch_storm/branch.py
branch_storm/constants.py
branch_storm/default/__init__.py
branch_storm/default/assign_results.py
branch_storm/default/parallelism.py
branch_storm/default/rw_classes.py
branch_storm/default/stubs.py
branch_storm/initialization_core.py
branch_storm/launch_operations/__init__.py
branch_storm/launch_operations/capture_manager.py
branch_storm/launch_operations/capture_manager.pyi
branch_storm/launch_operations/data_parsing.py
branch_storm/launch_operations/errors.py
branch_storm/operation.py
branch_storm/py.typed
branch_storm/type_containers.py
branch_storm/type_containers.pyi
branch_storm/utils/__init__.py
branch_storm/utils/common.py
branch_storm/utils/formatters.py
branch_storm/utils/options_utils.py
branch_storm-1.0.9.dist-info/METADATA
branch_storm-1.0.9.dist-info/WHEEL
branch_storm-1.0.9.dist-info/RECORD
