Metadata-Version: 2.3
Name: branch_storm
Version: 1.0.9
Summary: branch_storm package
Author: Dmitrii Zhitin
Author-email: 3271707@gmail.com
Requires-Python: >=3.9
Classifier: Programming Language :: Python :: 3
Classifier: Programming Language :: Python :: 3.9
Classifier: Programming Language :: Python :: 3.10
Classifier: Programming Language :: Python :: 3.11
Classifier: Programming Language :: Python :: 3.12
Classifier: Programming Language :: Python :: 3.13
Requires-Dist: typeguard (==4.4.1)
Project-URL: Repository, https://github.com/sls88/branch-storm
